{
  "POIs": [
    {
      "fit": [
        -0.2877587080001831,
        -5.4882773881104185e-09,
        0.319200724363327
      ],
      "name": "r"
    }
  ],
  "method": "default",
  "params": [
    {
      "fit": [
        -0.9899881482124329,
        0.0,
        0.9844898581504822
      ],
      "groups": [],
      "impact_r": 0.014821957796812057,
      "name": "JetEn",
      "prefit": [
        -0.9999999999999999,
        0.0,
        0.9999999999999999
      ],
      "r": [
        0.01250025536864996,
        0.0,
        -0.014821957796812057
      ],
      "type": "Gaussian"
    },
    {
      "fit": [
        -0.9871877431869507,
        -4.97991037295975e-10,
        0.984528124332428
      ],
      "groups": [],
      "impact_r": 0.010555832866318268,
      "name": "JetRes",
      "prefit": [
        -0.9999999999999999,
        0.0,
        0.9999999999999999
      ],
      "r": [
        -0.00994614977389574,
        2.1953110163064338e-10,
        -0.010555832646787167
      ],
      "type": "Gaussian"
    },
    {
      "fit": [
        -0.9938203692436218,
        -3.4390164049824534e-09,
        0.9933461546897888
      ],
      "groups": [],
      "impact_r": 0.004124318316552689,
      "name": "L1Prefire",
      "prefit": [
        -0.9999999999999999,
        0.0,
        0.9999999999999999
      ],
      "r": [
        0.004124296363443136,
        -2.1953109552441674e-08,
        -0.00405926164239645
      ],
      "type": "Gaussian"
    },
    {
      "fit": [
        -0.9851022362709045,
        -5.54185275447594e-09,
        0.9865853190422058
      ],
      "groups": [],
      "impact_r": 0.015164457527553132,
      "name": "MuonEn",
      "prefit": [
        -0.9999999999999999,
        0.0,
        0.9999999999999999
      ],
      "r": [
        -0.00830040406435728,
        4.390622088124019e-09,
        0.01516446191817522
      ],
      "type": "Gaussian"
    },
    {
      "fit": [
        -0.9928961992263794,
        -4.1293155561561434e-09,
        0.9928926229476929
      ],
      "groups": [],
      "impact_r": 0.004772742811564257,
      "name": "MuonIDSF",
      "prefit": [
        -0.9999999999999999,
        0.0,
        0.9999999999999999
      ],
      "r": [
        0.004772720858454704,
        -2.1953109552441674e-08,
        -0.0046711815521121025
      ],
      "type": "Gaussian"
    },
    {
      "fit": [
        -0.5699554085731506,
        0.0,
        0.5456231236457825
      ],
      "groups": [],
      "impact_r": 0.10707632452249527,
      "name": "Nonprompt",
      "prefit": [
        -0.9999999999999999,
        0.0,
        0.9999999999999999
      ],
      "r": [
        0.09879597276449203,
        0.0,
        -0.10707632452249527
      ],
      "type": "Gaussian"
    },
    {
      "fit": [
        -0.9940527081489563,
        0.0,
        0.9941660165786743
      ],
      "groups": [],
      "impact_r": 0.0034648606088012457,
      "name": "PileupReweight",
      "prefit": [
        -0.9999999999999999,
        0.0,
        0.9999999999999999
      ],
      "r": [
        0.0034648606088012457,
        0.0,
        -0.0034387344494462013
      ],
      "type": "Gaussian"
    },
    {
      "fit": [
        -0.993880569934845,
        6.861108469563559e-12,
        0.994342029094696
      ],
      "groups": [],
      "impact_r": 0.0011344174987452799,
      "name": "TriggerSF",
      "prefit": [
        -0.9999999999999999,
        0.0,
        0.9999999999999999
      ],
      "r": [
        0.0011344177182763815,
        2.1953110163064338e-10,
        -0.001134171849116683
      ],
      "type": "Gaussian"
    },
    {
      "fit": [
        -0.9901381731033325,
        0.0,
        0.9896053075790405
      ],
      "groups": [],
      "impact_r": 0.008455614559352398,
      "name": "lumi_13TeV",
      "prefit": [
        -0.9999999999999999,
        0.0,
        0.9999999999999999
      ],
      "r": [
        0.008455614559352398,
        0.0,
        -0.00812114030122757
      ],
      "type": "Gaussian"
    },
    {
      "fit": [
        -0.8375755548477173,
        -1.3546177797252312e-05,
        0.8771666884422302
      ],
      "groups": [],
      "impact_r": 0.004200676822097016,
      "name": "prop_binsignal_region_bin0",
      "prefit": [
        -0.9999999999999999,
        0.0,
        0.9999999999999999
      ],
      "r": [
        0.002377277472987771,
        -5.4882773881104185e-09,
        0.004200671333819628
      ],
      "type": "Gaussian"
    },
    {
      "fit": [
        -0.9537469744682312,
        -9.746644536789972e-06,
        0.9612796902656555
      ],
      "groups": [],
      "impact_r": 0.003169078745872689,
      "name": "prop_binsignal_region_bin1",
      "prefit": [
        -0.9999999999999999,
        0.0,
        0.9999999999999999
      ],
      "r": [
        0.0031690732575953007,
        -5.4882773881104185e-09,
        -0.00016089399287011474
      ],
      "type": "Gaussian"
    },
    {
      "fit": [
        -0.9399241805076599,
        -1.5354904462583363e-05,
        0.9459917545318604
      ],
      "groups": [],
      "impact_r": 0.003343364124179793,
      "name": "prop_binsignal_region_bin10",
      "prefit": [
        -0.9999999999999999,
        0.0,
        0.9999999999999999
      ],
      "r": [
        -0.0005536659737117589,
        -5.4882773881104185e-09,
        0.003343358635902405
      ],
      "type": "Gaussian"
    },
    {
      "fit": [
        -0.9440590739250183,
        -1.2263951248314697e-05,
        0.9498516321182251
      ],
      "groups": [],
      "impact_r": 0.004696978622109604,
      "name": "prop_binsignal_region_bin11",
      "prefit": [
        -0.9999999999999999,
        0.0,
        0.9999999999999999
      ],
      "r": [
        -0.002672050381079316,
        -5.4882773881104185e-09,
        0.004696973133832216
      ],
      "type": "Gaussian"
    },
    {
      "fit": [
        -0.8949249386787415,
        -1.5222560250549577e-05,
        0.9086083173751831
      ],
      "groups": [],
      "impact_r": 0.014191359181881857,
      "name": "prop_binsignal_region_bin12",
      "prefit": [
        -0.9999999999999999,
        0.0,
        0.9999999999999999
      ],
      "r": [
        -0.011603156104683876,
        -5.4882773881104185e-09,
        0.01419135369360447
      ],
      "type": "Gaussian"
    },
    {
      "fit": [
        -0.8930901288986206,
        -1.7235677660210058e-05,
        0.9067675471305847
      ],
      "groups": [],
      "impact_r": 0.023578518901945067,
      "name": "prop_binsignal_region_bin13",
      "prefit": [
        -0.9999999999999999,
        0.0,
        0.9999999999999999
      ],
      "r": [
        -0.02284538559615612,
        -5.4882773881104185e-09,
        0.02357851341366768
      ],
      "type": "Gaussian"
    },
    {
      "fit": [
        -0.8929494023323059,
        -1.7416277842130512e-05,
        0.9066083431243896
      ],
      "groups": [],
      "impact_r": 0.022652001951814604,
      "name": "prop_binsignal_region_bin14",
      "prefit": [
        -0.9999999999999999,
        0.0,
        0.9999999999999999
      ],
      "r": [
        -0.021649988368153572,
        -5.4882773881104185e-09,
        0.022651996463537216
      ],
      "type": "Gaussian"
    },
    {
      "fit": [
        -0.8337252736091614,
        -1.1819065548479557e-05,
        0.866953432559967
      ],
      "groups": [],
      "impact_r": 0.012529204499901248,
      "name": "prop_binsignal_region_bin2",
      "prefit": [
        -0.9999999999999999,
        0.0,
        0.9999999999999999
      ],
      "r": [
        -0.008850466459989548,
        -5.4882773881104185e-09,
        0.01252919901162386
      ],
      "type": "Gaussian"
    },
    {
      "fit": [
        -0.8624356985092163,
        -1.461641750211129e-05,
        0.8891492486000061
      ],
      "groups": [],
      "impact_r": 0.00822095376718135,
      "name": "prop_binsignal_region_bin3",
      "prefit": [
        -0.9999999999999999,
        0.0,
        0.9999999999999999
      ],
      "r": [
        -0.004142810124903917,
        -5.4882773881104185e-09,
        0.008220948278903961
      ],
      "type": "Gaussian"
    },
    {
      "fit": [
        -0.906457245349884,
        -2.1068726709927432e-05,
        0.922748327255249
      ],
      "groups": [],
      "impact_r": 0.006935601023019267,
      "name": "prop_binsignal_region_bin4",
      "prefit": [
        -0.9999999999999999,
        0.0,
        0.9999999999999999
      ],
      "r": [
        0.0069355955347418785,
        -5.4882773881104185e-09,
        -0.0014633639948442578
      ],
      "type": "Gaussian"
    },
    {
      "fit": [
        -0.8940039277076721,
        -4.586216891766526e-05,
        0.9127728343009949
      ],
      "groups": [],
      "impact_r": 0.028615999867201758,
      "name": "prop_binsignal_region_bin5",
      "prefit": [
        -0.9999999999999999,
        0.0,
        0.9999999999999999
      ],
      "r": [
        0.02861599437892437,
        -5.4882773881104185e-09,
        -0.01641196757555008
      ],
      "type": "Gaussian"
    },
    {
      "fit": [
        -0.9134256839752197,
        -9.111225517699495e-05,
        0.9228767156600952
      ],
      "groups": [],
      "impact_r": 0.06272926730382533,
      "name": "prop_binsignal_region_bin6",
      "prefit": [
        -0.9999999999999999,
        0.0,
        0.9999999999999999
      ],
      "r": [
        0.06272926181554794,
        -5.4882773881104185e-09,
        -0.043137215077877045
      ],
      "type": "Gaussian"
    },
    {
      "fit": [
        -0.9722692966461182,
        -0.00011116058158222586,
        0.9725369215011597
      ],
      "groups": [],
      "impact_r": 0.06934048784244151,
      "name": "prop_binsignal_region_bin7",
      "prefit": [
        -0.9999999999999999,
        0.0,
        0.9999999999999999
      ],
      "r": [
        0.06934048235416412,
        -5.4882773881104185e-09,
        -0.0639202669262886
      ],
      "type": "Gaussian"
    },
    {
      "fit": [
        -0.9362373948097229,
        -9.709190635476261e-05,
        0.9405815005302429
      ],
      "groups": [],
      "impact_r": 0.06554215950238795,
      "name": "prop_binsignal_region_bin8",
      "prefit": [
        -0.9999999999999999,
        0.0,
        0.9999999999999999
      ],
      "r": [
        0.06554215401411057,
        -5.4882773881104185e-09,
        -0.0505080372095108
      ],
      "type": "Gaussian"
    },
    {
      "fit": [
        -0.9020308256149292,
        -3.521738472045399e-05,
        0.9161263108253479
      ],
      "groups": [],
      "impact_r": 0.014262336206615878,
      "name": "prop_binsignal_region_bin9",
      "prefit": [
        -0.9999999999999999,
        0.0,
        0.9999999999999999
      ],
      "r": [
        0.01426233071833849,
        -5.4882773881104185e-09,
        -0.007681872695684433
      ],
      "type": "Gaussian"
    }
  ]
}