{
  "POIs": [
    {
      "fit": [
        -0.04349459707736969,
        5.399326818977812e-17,
        0.24632667005062103
      ],
      "name": "r"
    }
  ],
  "method": "default",
  "params": [
    {
      "fit": [
        -0.9940868020057678,
        0.0,
        0.9943843483924866
      ],
      "groups": [],
      "impact_r": 1.440153027996863e-06,
      "name": "ElectronEn",
      "prefit": [
        -0.9999999999999999,
        0.0,
        0.9999999999999999
      ],
      "r": [
        4.6865582703503605e-07,
        5.399326818977812e-17,
        -1.4401530279428698e-06
      ],
      "type": "Gaussian"
    },
    {
      "fit": [
        -0.9938752055168152,
        0.0,
        0.9943472743034363
      ],
      "groups": [],
      "impact_r": 0.0006559231551363668,
      "name": "ElectronIDSF",
      "prefit": [
        -0.9999999999999999,
        0.0,
        0.9999999999999999
      ],
      "r": [
        0.0006559231551364064,
        3.957337929572091e-17,
        -0.000652338145300746
      ],
      "type": "Gaussian"
    },
    {
      "fit": [
        -0.9940868020057678,
        0.0,
        0.9943844676017761
      ],
      "groups": [],
      "impact_r": 0.0,
      "name": "ElectronRes",
      "prefit": [
        -0.9999999999999999,
        0.0,
        0.9999999999999999
      ],
      "r": [
        5.399326818977812e-17,
        5.399326818977812e-17,
        5.399326818977812e-17
      ],
      "type": "Gaussian"
    },
    {
      "fit": [
        -0.9935562014579773,
        4.336808689942018e-19,
        0.9943340420722961
      ],
      "groups": [],
      "impact_r": 0.001428936491720325,
      "name": "JetEn",
      "prefit": [
        -0.9999999999999999,
        0.0,
        0.9999999999999999
      ],
      "r": [
        0.0014289364917203784,
        5.323432666903827e-17,
        -0.0005588478525169194
      ],
      "type": "Gaussian"
    },
    {
      "fit": [
        -0.9915075302124023,
        2.6020852139652106e-17,
        0.9914869666099548
      ],
      "groups": [],
      "impact_r": 0.002559792483225592,
      "name": "JetRes_16b",
      "prefit": [
        -0.9999999999999999,
        0.0,
        0.9999999999999999
      ],
      "r": [
        -0.001895411522127688,
        1.2696007439805257e-16,
        -0.002559792483225465
      ],
      "type": "Gaussian"
    },
    {
      "fit": [
        -0.9938698410987854,
        0.0,
        0.9943527579307556
      ],
      "groups": [],
      "impact_r": 0.0003822380385826704,
      "name": "L1Prefire_16b",
      "prefit": [
        -0.9999999999999999,
        0.0,
        0.9999999999999999
      ],
      "r": [
        0.0003822380385827273,
        5.692061405548898e-17,
        -0.0003810475755017251
      ],
      "type": "Gaussian"
    },
    {
      "fit": [
        -0.9929012656211853,
        4.336808689942018e-19,
        0.9928074479103088
      ],
      "groups": [],
      "impact_r": 0.0008370209252461327,
      "name": "MuonEn",
      "prefit": [
        -0.9999999999999999,
        0.0,
        0.9999999999999999
      ],
      "r": [
        0.0007190042524598539,
        4.640385298237959e-17,
        0.0008370209252461791
      ],
      "type": "Gaussian"
    },
    {
      "fit": [
        -0.9938725233078003,
        0.0,
        0.994350016117096
      ],
      "groups": [],
      "impact_r": 0.0006127094966358897,
      "name": "MuonIDSF",
      "prefit": [
        -0.9999999999999999,
        0.0,
        0.9999999999999999
      ],
      "r": [
        0.0006127094966359437,
        5.399326818977812e-17,
        -0.0006126909865997732
      ],
      "type": "Gaussian"
    },
    {
      "fit": [
        -0.9686885476112366,
        -6.071532165918825e-18,
        0.9655737280845642
      ],
      "groups": [],
      "impact_r": 0.00765591626986853,
      "name": "Nonprompt_16b",
      "prefit": [
        -0.9999999999999999,
        0.0,
        0.9999999999999999
      ],
      "r": [
        0.007655916269868612,
        8.239936510889834e-17,
        -0.005627108737826347
      ],
      "type": "Gaussian"
    },
    {
      "fit": [
        -0.9940868020057678,
        0.0,
        0.9943844676017761
      ],
      "groups": [],
      "impact_r": 0.0,
      "name": "PDF",
      "prefit": [
        -0.9999999999999999,
        0.0,
        0.9999999999999999
      ],
      "r": [
        5.399326818977812e-17,
        5.399326818977812e-17,
        5.399326818977812e-17
      ],
      "type": "Gaussian"
    },
    {
      "fit": [
        -0.9940868020057678,
        0.0,
        0.9943844676017761
      ],
      "groups": [],
      "impact_r": 0.0,
      "name": "PS",
      "prefit": [
        -0.9999999999999999,
        0.0,
        0.9999999999999999
      ],
      "r": [
        5.399326818977812e-17,
        5.399326818977812e-17,
        5.399326818977812e-17
      ],
      "type": "Gaussian"
    },
    {
      "fit": [
        -0.9941633343696594,
        0.0,
        0.9939334988594055
      ],
      "groups": [],
      "impact_r": 0.0038470318540931208,
      "name": "PileupReweight",
      "prefit": [
        -0.9999999999999999,
        0.0,
        0.9999999999999999
      ],
      "r": [
        0.0033632097765803337,
        4.607859233063394e-17,
        -0.003847031854093075
      ],
      "type": "Gaussian"
    },
    {
      "fit": [
        -0.9940868020057678,
        0.0,
        0.9943844676017761
      ],
      "groups": [],
      "impact_r": 0.0,
      "name": "Scale",
      "prefit": [
        -0.9999999999999999,
        0.0,
        0.9999999999999999
      ],
      "r": [
        5.399326818977812e-17,
        5.399326818977812e-17,
        5.399326818977812e-17
      ],
      "type": "Gaussian"
    },
    {
      "fit": [
        -0.9938936233520508,
        0.0,
        0.9943281412124634
      ],
      "groups": [],
      "impact_r": 0.0012645592214539018,
      "name": "TriggerSF",
      "prefit": [
        -0.9999999999999999,
        0.0,
        0.9999999999999999
      ],
      "r": [
        0.0012645592214539647,
        6.288372600415926e-17,
        -0.0011858686339110136
      ],
      "type": "Gaussian"
    },
    {
      "fit": [
        -0.9938838481903076,
        0.0,
        0.9943383932113647
      ],
      "groups": [],
      "impact_r": 0.0009853017982094552,
      "name": "lumi_13TeV",
      "prefit": [
        -0.9999999999999999,
        0.0,
        0.9999999999999999
      ],
      "r": [
        0.000985301798209548,
        9.269928574751063e-17,
        -0.0009721870883367956
      ],
      "type": "Gaussian"
    },
    {
      "fit": [
        -0.9939242601394653,
        0.0,
        0.9942858815193176
      ],
      "groups": [],
      "impact_r": 0.0015610362170264637,
      "name": "norm_WZ",
      "prefit": [
        -0.9999999999999999,
        0.0,
        0.9999999999999999
      ],
      "r": [
        0.0013792630052194,
        5.106592232406726e-17,
        -0.0015610362170264125
      ],
      "type": "Gaussian"
    },
    {
      "fit": [
        -0.9938696026802063,
        0.0,
        0.9943527579307556
      ],
      "groups": [],
      "impact_r": 0.0002882565022446652,
      "name": "norm_ZZ",
      "prefit": [
        -0.9999999999999999,
        0.0,
        0.9999999999999999
      ],
      "r": [
        0.00027181929908692837,
        4.369334755116583e-17,
        -0.0002882565022446215
      ],
      "type": "Gaussian"
    },
    {
      "fit": [
        -0.9939297437667847,
        0.0,
        0.9941962361335754
      ],
      "groups": [],
      "impact_r": 0.0018006488680839964,
      "name": "norm_others",
      "prefit": [
        -0.9999999999999999,
        0.0,
        0.9999999999999999
      ],
      "r": [
        0.0012589546386152506,
        4.2500725161431774e-17,
        -0.0018006488680839539
      ],
      "type": "Gaussian"
    },
    {
      "fit": [
        -0.9938772320747375,
        0.0,
        0.9943435192108154
      ],
      "groups": [],
      "impact_r": 0.0006268055876717779,
      "name": "norm_ttH",
      "prefit": [
        -0.9999999999999999,
        0.0,
        0.9999999999999999
      ],
      "r": [
        0.0005614474066533148,
        8.077306185017008e-17,
        -0.0006268055876716971
      ],
      "type": "Gaussian"
    },
    {
      "fit": [
        -0.9938697218894958,
        0.0,
        0.9943522810935974
      ],
      "groups": [],
      "impact_r": 0.0002194330736529994,
      "name": "norm_ttW",
      "prefit": [
        -0.9999999999999999,
        0.0,
        0.9999999999999999
      ],
      "r": [
        0.00019931091810576618,
        9.118140270603092e-17,
        -0.0002194330736529082
      ],
      "type": "Gaussian"
    },
    {
      "fit": [
        -0.9939626455307007,
        0.0,
        0.9942349791526794
      ],
      "groups": [],
      "impact_r": 0.0014313390711323017,
      "name": "norm_ttZ",
      "prefit": [
        -0.9999999999999999,
        0.0,
        0.9999999999999999
      ],
      "r": [
        0.001333696534857154,
        5.887217796596289e-17,
        -0.0014313390711322427
      ],
      "type": "Gaussian"
    },
    {
      "fit": [
        0.9039233326911926,
        2.0,
        3.7463467121124268
      ],
      "groups": [],
      "impact_r": 0.00014741549966851438,
      "name": "prop_binsignal_region_bin0_WZ",
      "prefit": [
        0.897575384672683,
        1.9999999999999993,
        3.7654321135285054
      ],
      "r": [
        0.00014741549966856837,
        5.399326818977812e-17,
        -0.00010247691534459591
      ],
      "type": "Poisson"
    },
    {
      "fit": [
        2.325439929962158,
        4.0,
        6.3316426277160645
      ],
      "groups": [],
      "impact_r": 6.661752195267915e-06,
      "name": "prop_binsignal_region_bin0_ZZ",
      "prefit": [
        2.318494152717885,
        3.9999999999999996,
        6.346328819503796
      ],
      "r": [
        5.031215096096275e-06,
        5.399326818977812e-17,
        -6.661752195213921e-06
      ],
      "type": "Poisson"
    },
    {
      "fit": [
        2.3254313468933105,
        4.0,
        6.331630229949951
      ],
      "groups": [],
      "impact_r": 1.0691405805172841e-05,
      "name": "prop_binsignal_region_bin0_others",
      "prefit": [
        2.318494152717885,
        3.9999999999999996,
        6.346328819503796
      ],
      "r": [
        8.242044714279473e-06,
        5.399326818977812e-17,
        -1.0691405805118848e-05
      ],
      "type": "Poisson"
    },
    {
      "fit": [
        -0.9938669800758362,
        0.0,
        0.9943556189537048
      ],
      "groups": [],
      "impact_r": 0.0,
      "name": "prop_binsignal_region_bin0_signal",
      "prefit": [
        -0.9999999999999999,
        0.0,
        0.9999999999999999
      ],
      "r": [
        5.399326818977812e-17,
        5.399326818977812e-17,
        5.399326818977812e-17
      ],
      "type": "Gaussian"
    },
    {
      "fit": [
        0.9026792049407959,
        2.0,
        3.7536213397979736
      ],
      "groups": [],
      "impact_r": 2.1168185412588506e-05,
      "name": "prop_binsignal_region_bin0_ttH",
      "prefit": [
        0.897575384672683,
        1.9999999999999993,
        3.7654321135285054
      ],
      "r": [
        1.5043008716020267e-05,
        5.399326818977812e-17,
        -2.1168185412534513e-05
      ],
      "type": "Poisson"
    },
    {
      "fit": [
        -0.9939612746238708,
        0.0,
        0.9942752122879028
      ],
      "groups": [],
      "impact_r": 3.187049151165411e-05,
      "name": "prop_binsignal_region_bin0_ttW",
      "prefit": [
        -0.9999999999999999,
        0.0,
        0.9999999999999999
      ],
      "r": [
        3.187049151165411e-05,
        0.0,
        -2.618130383780226e-05
      ],
      "type": "Gaussian"
    },
    {
      "fit": [
        1.590923547744751,
        3.0,
        5.06674861907959
      ],
      "groups": [],
      "impact_r": 3.5104152630137256e-05,
      "name": "prop_binsignal_region_bin0_ttZ",
      "prefit": [
        1.5839744900812804,
        2.9999999999999996,
        5.080237864900868
      ],
      "r": [
        2.995694740093313e-05,
        5.399326818977812e-17,
        -3.510415263008326e-05
      ],
      "type": "Poisson"
    },
    {
      "fit": [
        -0.9918422698974609,
        1.734723475976807e-18,
        0.9931755661964417
      ],
      "groups": [],
      "impact_r": 0.0019559497013687615,
      "name": "prop_binsignal_region_bin10_WZ",
      "prefit": [
        -0.9999999999999999,
        0.0,
        0.9999999999999999
      ],
      "r": [
        0.0019559497013688087,
        4.716279450311944e-17,
        -0.0007589042070321739
      ],
      "type": "Gaussian"
    },
    {
      "fit": [
        6.336777687072754,
        9.0,
        12.320382118225098
      ],
      "groups": [],
      "impact_r": 0.0002131578221452031,
      "name": "prop_binsignal_region_bin10_ZZ",
      "prefit": [
        6.323656065133866,
        9.0,
        12.342190372334024
      ],
      "r": [
        0.0002026472066063434,
        5.399326818977812e-17,
        -0.0002131578221451491
      ],
      "type": "Poisson"
    },
    {
      "fit": [
        2.3254446983337402,
        4.0,
        6.331650257110596
      ],
      "groups": [],
      "impact_r": 1.6164960470686643e-05,
      "name": "prop_binsignal_region_bin10_others",
      "prefit": [
        2.318494152717885,
        3.9999999999999996,
        6.346328819503796
      ],
      "r": [
        1.1795011232607067e-05,
        5.399326818977812e-17,
        -1.616496047063265e-05
      ],
      "type": "Poisson"
    },
    {
      "fit": [
        -0.9938669800758362,
        0.0,
        0.9943556189537048
      ],
      "groups": [],
      "impact_r": 0.0,
      "name": "prop_binsignal_region_bin10_signal",
      "prefit": [
        -0.9999999999999999,
        0.0,
        0.9999999999999999
      ],
      "r": [
        5.399326818977812e-17,
        5.399326818977812e-17,
        5.399326818977812e-17
      ],
      "type": "Gaussian"
    },
    {
      "fit": [
        2.32590651512146,
        4.0,
        6.330817222595215
      ],
      "groups": [],
      "impact_r": 0.00042618330917315746,
      "name": "prop_binsignal_region_bin10_ttH",
      "prefit": [
        2.318494152717885,
        3.9999999999999996,
        6.346328819503796
      ],
      "r": [
        0.00042618330917321146,
        5.399326818977812e-17,
        -0.00041932309977710247
      ],
      "type": "Poisson"
    },
    {
      "fit": [
        -0.9939908385276794,
        0.0,
        0.9942591190338135
      ],
      "groups": [],
      "impact_r": 0.00042617158032950205,
      "name": "prop_binsignal_region_bin10_ttW",
      "prefit": [
        -0.9999999999999999,
        0.0,
        0.9999999999999999
      ],
      "r": [
        0.0004261715803295374,
        3.5344990823027445e-17,
        -0.00031649533775635064
      ],
      "type": "Gaussian"
    },
    {
      "fit": [
        0.9024231433868408,
        2.0,
        3.752215623855591
      ],
      "groups": [],
      "impact_r": 0.0005490152398124877,
      "name": "prop_binsignal_region_bin10_ttZ",
      "prefit": [
        0.897575384672683,
        1.9999999999999993,
        3.7654321135285054
      ],
      "r": [
        0.0005402552196756005,
        5.399326818977812e-17,
        -0.0005490152398124337
      ],
      "type": "Poisson"
    },
    {
      "fit": [
        5.507686138153076,
        8.0,
        11.151421546936035
      ],
      "groups": [],
      "impact_r": 1.532406827263336e-06,
      "name": "prop_binsignal_region_bin11_ZZ",
      "prefit": [
        5.4946151438321795,
        8.0,
        11.17112957382017
      ],
      "r": [
        1.2672039702010807e-06,
        5.399326818977812e-17,
        -1.5324068272093427e-06
      ],
      "type": "Poisson"
    },
    {
      "fit": [
        0.40615272521972656,
        1.0,
        2.0066518783569336
      ],
      "groups": [],
      "impact_r": 0.0006610022974200007,
      "name": "prop_binsignal_region_bin11_nonprompt",
      "prefit": [
        0.30170955445432013,
        1.0000000000000002,
        2.357685579639466
      ],
      "r": [
        0.0004916023463010788,
        5.399326818977812e-17,
        0.0006610022974200547
      ],
      "type": "Poisson"
    },
    {
      "fit": [
        0.3041205108165741,
        1.0,
        2.3477327823638916
      ],
      "groups": [],
      "impact_r": 1.1283774484212392e-06,
      "name": "prop_binsignal_region_bin11_others",
      "prefit": [
        0.30170955445432013,
        1.0000000000000002,
        2.357685579639466
      ],
      "r": [
        6.269245886869612e-07,
        5.399326818977812e-17,
        -1.128377448367246e-06
      ],
      "type": "Poisson"
    },
    {
      "fit": [
        -0.9938669800758362,
        0.0,
        0.9943556189537048
      ],
      "groups": [],
      "impact_r": 0.0,
      "name": "prop_binsignal_region_bin11_signal",
      "prefit": [
        -0.9999999999999999,
        0.0,
        0.9999999999999999
      ],
      "r": [
        5.399326818977812e-17,
        5.399326818977812e-17,
        5.399326818977812e-17
      ],
      "type": "Gaussian"
    },
    {
      "fit": [
        2.3254430294036865,
        4.0,
        6.3316473960876465
      ],
      "groups": [],
      "impact_r": 3.0537944440396734e-06,
      "name": "prop_binsignal_region_bin11_ttH",
      "prefit": [
        2.318494152717885,
        3.9999999999999996,
        6.346328819503796
      ],
      "r": [
        2.257536834804341e-06,
        5.399326818977812e-17,
        -3.05379444398568e-06
      ],
      "type": "Poisson"
    },
    {
      "fit": [
        -0.993868887424469,
        0.0,
        0.9943537712097168
      ],
      "groups": [],
      "impact_r": 3.611367446830927e-06,
      "name": "prop_binsignal_region_bin11_ttZ",
      "prefit": [
        -0.9999999999999999,
        0.0,
        0.9999999999999999
      ],
      "r": [
        3.611367446865188e-06,
        3.426078865054194e-17,
        -3.5226316867920104e-06
      ],
      "type": "Gaussian"
    },
    {
      "fit": [
        7.176485061645508,
        10.0,
        13.481273651123047
      ],
      "groups": [],
      "impact_r": 2.5831095626980974e-05,
      "name": "prop_binsignal_region_bin12_ZZ",
      "prefit": [
        7.161895381748982,
        10.0,
        13.504032638931708
      ],
      "r": [
        2.4137983928085305e-05,
        5.399326818977812e-17,
        -2.583109562692698e-05
      ],
      "type": "Poisson"
    },
    {
      "fit": [
        1.5896613597869873,
        3.0,
        5.066864013671875
      ],
      "groups": [],
      "impact_r": 1.959523069677686e-05,
      "name": "prop_binsignal_region_bin12_others",
      "prefit": [
        1.5839744900812804,
        2.9999999999999996,
        5.080237864900868
      ],
      "r": [
        1.4772627764614299e-05,
        5.399326818977812e-17,
        -1.9595230696722865e-05
      ],
      "type": "Poisson"
    },
    {
      "fit": [
        -0.9938669800758362,
        0.0,
        0.9943556189537048
      ],
      "groups": [],
      "impact_r": 0.0,
      "name": "prop_binsignal_region_bin12_signal",
      "prefit": [
        -0.9999999999999999,
        0.0,
        0.9999999999999999
      ],
      "r": [
        5.399326818977812e-17,
        5.399326818977812e-17,
        5.399326818977812e-17
      ],
      "type": "Gaussian"
    },
    {
      "fit": [
        0.9026607275009155,
        2.0,
        3.7535924911499023
      ],
      "groups": [],
      "impact_r": 3.97908515879493e-05,
      "name": "prop_binsignal_region_bin12_ttH",
      "prefit": [
        0.897575384672683,
        1.9999999999999993,
        3.7654321135285054
      ],
      "r": [
        3.0404085919144563e-05,
        5.399326818977812e-17,
        -3.9790851587895304e-05
      ],
      "type": "Poisson"
    },
    {
      "fit": [
        -0.9938780665397644,
        0.0,
        0.9943453073501587
      ],
      "groups": [],
      "impact_r": 1.9123439415071183e-05,
      "name": "prop_binsignal_region_bin12_ttW",
      "prefit": [
        -0.9999999999999999,
        0.0,
        0.9999999999999999
      ],
      "r": [
        1.9123439415125176e-05,
        5.399326818977812e-17,
        -1.724128014757298e-05
      ],
      "type": "Gaussian"
    },
    {
      "fit": [
        2.3270771503448486,
        4.0,
        6.328737258911133
      ],
      "groups": [],
      "impact_r": 0.00010823982302094067,
      "name": "prop_binsignal_region_bin12_ttZ",
      "prefit": [
        2.318494152717885,
        3.9999999999999996,
        6.346328819503796
      ],
      "r": [
        0.00010823982302099466,
        5.399326818977812e-17,
        -8.764748054090887e-05
      ],
      "type": "Poisson"
    },
    {
      "fit": [
        -0.9932462573051453,
        0.0,
        0.9941073656082153
      ],
      "groups": [],
      "impact_r": 3.3851611078671495e-05,
      "name": "prop_binsignal_region_bin13_WZ",
      "prefit": [
        -0.9999999999999999,
        0.0,
        0.9999999999999999
      ],
      "r": [
        3.3851611078716815e-05,
        4.5319650809894085e-17,
        -2.2334921595756896e-05
      ],
      "type": "Gaussian"
    },
    {
      "fit": [
        3.0923190116882324,
        5.0,
        7.565345764160156
      ],
      "groups": [],
      "impact_r": 6.720290912252827e-06,
      "name": "prop_binsignal_region_bin13_ZZ",
      "prefit": [
        3.084097908968684,
        5.0,
        7.581106198937643
      ],
      "r": [
        5.543247425521258e-06,
        5.399326818977812e-17,
        -6.720290912198834e-06
      ],
      "type": "Poisson"
    },
    {
      "fit": [
        0.9026833772659302,
        2.0,
        3.7536308765411377
      ],
      "groups": [],
      "impact_r": 1.1478351552850078e-05,
      "name": "prop_binsignal_region_bin13_others",
      "prefit": [
        0.897575384672683,
        1.9999999999999993,
        3.7654321135285054
      ],
      "r": [
        8.42393910716055e-06,
        5.399326818977812e-17,
        -1.1478351552796084e-05
      ],
      "type": "Poisson"
    },
    {
      "fit": [
        -0.9938669800758362,
        0.0,
        0.9943556189537048
      ],
      "groups": [],
      "impact_r": 0.0,
      "name": "prop_binsignal_region_bin13_signal",
      "prefit": [
        -0.9999999999999999,
        0.0,
        0.9999999999999999
      ],
      "r": [
        5.399326818977812e-17,
        5.399326818977812e-17,
        5.399326818977812e-17
      ],
      "type": "Gaussian"
    },
    {
      "fit": [
        2.325928211212158,
        4.0,
        6.3308796882629395
      ],
      "groups": [],
      "impact_r": 1.8674269085803977e-05,
      "name": "prop_binsignal_region_bin13_ttH",
      "prefit": [
        2.318494152717885,
        3.9999999999999996,
        6.346328819503796
      ],
      "r": [
        1.779776721377857e-05,
        5.399326818977812e-17,
        -1.8674269085749984e-05
      ],
      "type": "Poisson"
    },
    {
      "fit": [
        -0.9939630031585693,
        0.0,
        0.9942779541015625
      ],
      "groups": [],
      "impact_r": 1.94638341781126e-05,
      "name": "prop_binsignal_region_bin13_ttW",
      "prefit": [
        -0.9999999999999999,
        0.0,
        0.9999999999999999
      ],
      "r": [
        1.9463834178168327e-05,
        5.572799166575493e-17,
        -1.4980780179030262e-05
      ],
      "type": "Gaussian"
    },
    {
      "fit": [
        1.5904548168182373,
        3.0,
        5.064508438110352
      ],
      "groups": [],
      "impact_r": 4.067088957521322e-05,
      "name": "prop_binsignal_region_bin13_ttZ",
      "prefit": [
        1.5839744900812804,
        2.9999999999999996,
        5.080237864900868
      ],
      "r": [
        4.067088957526721e-05,
        5.399326818977812e-17,
        -3.3788641303544864e-05
      ],
      "type": "Poisson"
    },
    {
      "fit": [
        -0.8233839869499207,
        0.0,
        0.9893357753753662
      ],
      "groups": [],
      "impact_r": 2.5158054995699786e-05,
      "name": "prop_binsignal_region_bin14_WZ",
      "prefit": [
        -0.9999999999999999,
        0.0,
        0.9999999999999999
      ],
      "r": [
        0.0,
        0.0,
        -2.5158054995699786e-05
      ],
      "type": "Gaussian"
    },
    {
      "fit": [
        4.688365459442139,
        7.0,
        9.970423698425293
      ],
      "groups": [],
      "impact_r": 3.3101587178492684e-06,
      "name": "prop_binsignal_region_bin14_ZZ",
      "prefit": [
        4.676546212856283,
        7.0,
        9.989068255581575
      ],
      "r": [
        3.0385419904632727e-06,
        5.399326818977812e-17,
        -3.310158717795275e-06
      ],
      "type": "Poisson"
    },
    {
      "fit": [
        0.9026978015899658,
        2.0,
        3.7536604404449463
      ],
      "groups": [],
      "impact_r": 3.7742343011444666e-06,
      "name": "prop_binsignal_region_bin14_others",
      "prefit": [
        0.897575384672683,
        1.9999999999999993,
        3.7654321135285054
      ],
      "r": [
        2.803027882691822e-06,
        5.399326818977812e-17,
        -3.7742343010904733e-06
      ],
      "type": "Poisson"
    },
    {
      "fit": [
        7.176504135131836,
        10.0,
        13.483833312988281
      ],
      "groups": [],
      "impact_r": 0.0,
      "name": "prop_binsignal_region_bin14_signal",
      "prefit": [
        7.161895381748982,
        10.0,
        13.504032638931708
      ],
      "r": [
        5.399326818977812e-17,
        5.399326818977812e-17,
        5.399326818977812e-17
      ],
      "type": "Poisson"
    },
    {
      "fit": [
        0.9026547074317932,
        2.0,
        3.7535877227783203
      ],
      "groups": [],
      "impact_r": 6.644689619915304e-06,
      "name": "prop_binsignal_region_bin14_ttH",
      "prefit": [
        0.897575384672683,
        1.9999999999999993,
        3.7654321135285054
      ],
      "r": [
        5.5841810535639524e-06,
        5.399326818977812e-17,
        -6.64468961986131e-06
      ],
      "type": "Poisson"
    },
    {
      "fit": [
        -0.9941085577011108,
        0.0,
        0.9941979050636292
      ],
      "groups": [],
      "impact_r": 1.3854138160185976e-05,
      "name": "prop_binsignal_region_bin14_ttW",
      "prefit": [
        -0.9999999999999999,
        0.0,
        0.9999999999999999
      ],
      "r": [
        1.3854138160240836e-05,
        5.4860629927766524e-17,
        -8.443670594715513e-06
      ],
      "type": "Gaussian"
    },
    {
      "fit": [
        -0.9936980605125427,
        8.673617379884035e-19,
        0.9938579201698303
      ],
      "groups": [],
      "impact_r": 2.6494808480410502e-05,
      "name": "prop_binsignal_region_bin14_ttZ",
      "prefit": [
        -0.9999999999999999,
        0.0,
        0.9999999999999999
      ],
      "r": [
        2.6494808480492793e-05,
        8.229094489164979e-17,
        -1.1952739441767335e-05
      ],
      "type": "Gaussian"
    },
    {
      "fit": [
        4.688380241394043,
        7.0,
        9.970446586608887
      ],
      "groups": [],
      "impact_r": 4.820422418615059e-06,
      "name": "prop_binsignal_region_bin1_ZZ",
      "prefit": [
        4.676546212856283,
        7.0,
        9.989068255581575
      ],
      "r": [
        3.876828031934565e-06,
        5.399326818977812e-17,
        -4.8204224185610656e-06
      ],
      "type": "Poisson"
    },
    {
      "fit": [
        0.3302125930786133,
        1.0,
        2.2339398860931396
      ],
      "groups": [],
      "impact_r": 0.0006755530484951493,
      "name": "prop_binsignal_region_bin1_nonprompt",
      "prefit": [
        0.30170955445432013,
        1.0000000000000002,
        2.357685579639466
      ],
      "r": [
        0.0006755530484952033,
        5.399326818977812e-17,
        -0.00024323794059455395
      ],
      "type": "Poisson"
    },
    {
      "fit": [
        0.9027130007743835,
        2.0,
        3.753695249557495
      ],
      "groups": [],
      "impact_r": 1.929554855504981e-06,
      "name": "prop_binsignal_region_bin1_others",
      "prefit": [
        0.897575384672683,
        1.9999999999999993,
        3.7654321135285054
      ],
      "r": [
        1.2655472119149636e-06,
        5.399326818977812e-17,
        -1.929554855450988e-06
      ],
      "type": "Poisson"
    },
    {
      "fit": [
        -0.9938669800758362,
        0.0,
        0.9943556189537048
      ],
      "groups": [],
      "impact_r": 0.0,
      "name": "prop_binsignal_region_bin1_signal",
      "prefit": [
        -0.9999999999999999,
        0.0,
        0.9999999999999999
      ],
      "r": [
        5.399326818977812e-17,
        5.399326818977812e-17,
        5.399326818977812e-17
      ],
      "type": "Gaussian"
    },
    {
      "fit": [
        2.3254261016845703,
        4.0,
        6.3316216468811035
      ],
      "groups": [],
      "impact_r": 9.211293218012876e-06,
      "name": "prop_binsignal_region_bin1_ttH",
      "prefit": [
        2.318494152717885,
        3.9999999999999996,
        6.346328819503796
      ],
      "r": [
        6.901957476657117e-06,
        5.399326818977812e-17,
        -9.211293217958882e-06
      ],
      "type": "Poisson"
    },
    {
      "fit": [
        0.9027110934257507,
        2.0,
        3.753690481185913
      ],
      "groups": [],
      "impact_r": 4.304924004881619e-06,
      "name": "prop_binsignal_region_bin1_ttW",
      "prefit": [
        0.897575384672683,
        1.9999999999999993,
        3.7654321135285054
      ],
      "r": [
        2.7849889647768578e-06,
        5.399326818977812e-17,
        -4.304924004827626e-06
      ],
      "type": "Poisson"
    },
    {
      "fit": [
        0.902676522731781,
        2.0,
        3.753612518310547
      ],
      "groups": [],
      "impact_r": 1.6553351088131755e-05,
      "name": "prop_binsignal_region_bin1_ttZ",
      "prefit": [
        0.897575384672683,
        1.9999999999999993,
        3.7654321135285054
      ],
      "r": [
        1.1044237908208743e-05,
        5.399326818977812e-17,
        -1.655335108807776e-05
      ],
      "type": "Poisson"
    },
    {
      "fit": [
        0.30404627323150635,
        1.0,
        2.3472900390625
      ],
      "groups": [],
      "impact_r": 3.870602085958978e-05,
      "name": "prop_binsignal_region_bin2_WZ",
      "prefit": [
        0.30170955445432013,
        1.0000000000000002,
        2.357685579639466
      ],
      "r": [
        2.2100146452430636e-05,
        5.399326818977812e-17,
        -3.8706020859535784e-05
      ],
      "type": "Poisson"
    },
    {
      "fit": [
        6.336826801300049,
        9.0,
        12.322871208190918
      ],
      "groups": [],
      "impact_r": 5.1160482144581385e-06,
      "name": "prop_binsignal_region_bin2_ZZ",
      "prefit": [
        6.323656065133866,
        9.0,
        12.342190372334024
      ],
      "r": [
        4.217190507915802e-06,
        5.399326818977812e-17,
        -5.116048214404145e-06
      ],
      "type": "Poisson"
    },
    {
      "fit": [
        0.326824814081192,
        1.0,
        2.2467024326324463
      ],
      "groups": [],
      "impact_r": 0.0008900918764993008,
      "name": "prop_binsignal_region_bin2_nonprompt",
      "prefit": [
        0.30170955445432013,
        1.0000000000000002,
        2.357685579639466
      ],
      "r": [
        0.0008900918764993548,
        5.399326818977812e-17,
        -0.00032738837762735784
      ],
      "type": "Poisson"
    },
    {
      "fit": [
        2.3254430294036865,
        4.0,
        6.3316473960876465
      ],
      "groups": [],
      "impact_r": 4.294416612592037e-06,
      "name": "prop_binsignal_region_bin2_others",
      "prefit": [
        2.318494152717885,
        3.9999999999999996,
        6.346328819503796
      ],
      "r": [
        3.1739277801534627e-06,
        5.399326818977812e-17,
        -4.294416612538043e-06
      ],
      "type": "Poisson"
    },
    {
      "fit": [
        -0.9938669800758362,
        0.0,
        0.9943556189537048
      ],
      "groups": [],
      "impact_r": 0.0,
      "name": "prop_binsignal_region_bin2_signal",
      "prefit": [
        -0.9999999999999999,
        0.0,
        0.9999999999999999
      ],
      "r": [
        5.399326818977812e-17,
        5.399326818977812e-17,
        5.399326818977812e-17
      ],
      "type": "Gaussian"
    },
    {
      "fit": [
        1.5896589756011963,
        3.0,
        5.066860675811768
      ],
      "groups": [],
      "impact_r": 1.3684175428406312e-05,
      "name": "prop_binsignal_region_bin2_ttH",
      "prefit": [
        1.5839744900812804,
        2.9999999999999996,
        5.080237864900868
      ],
      "r": [
        9.745152965479065e-06,
        5.399326818977812e-17,
        -1.3684175428352319e-05
      ],
      "type": "Poisson"
    },
    {
      "fit": [
        -0.9938809871673584,
        0.0,
        0.9943419694900513
      ],
      "groups": [],
      "impact_r": 1.32828499772046e-05,
      "name": "prop_binsignal_region_bin2_ttZ",
      "prefit": [
        -0.9999999999999999,
        0.0,
        0.9999999999999999
      ],
      "r": [
        1.3282849977258593e-05,
        5.399326818977812e-17,
        -1.2691894880845211e-05
      ],
      "type": "Gaussian"
    },
    {
      "fit": [
        0.3042607605457306,
        1.0,
        2.344815254211426
      ],
      "groups": [],
      "impact_r": 0.0003186381363776121,
      "name": "prop_binsignal_region_bin3_WZ",
      "prefit": [
        0.30170955445432013,
        1.0000000000000002,
        2.357685579639466
      ],
      "r": [
        0.0002788676356431097,
        5.399326818977812e-17,
        -0.0003186381363775581
      ],
      "type": "Poisson"
    },
    {
      "fit": [
        3.881307601928711,
        6.0,
        8.77540111541748
      ],
      "groups": [],
      "impact_r": 4.8585938202504045e-05,
      "name": "prop_binsignal_region_bin3_ZZ",
      "prefit": [
        3.8718786486154335,
        6.0,
        8.793563398676877
      ],
      "r": [
        4.00385724788066e-05,
        5.399326818977812e-17,
        -4.858593820245005e-05
      ],
      "type": "Poisson"
    },
    {
      "fit": [
        4.688333511352539,
        7.0,
        9.97037124633789
      ],
      "groups": [],
      "impact_r": 8.27250478324089e-05,
      "name": "prop_binsignal_region_bin3_others",
      "prefit": [
        4.676546212856283,
        7.0,
        9.989068255581575
      ],
      "r": [
        7.356855348916724e-05,
        5.399326818977812e-17,
        -8.27250478323549e-05
      ],
      "type": "Poisson"
    },
    {
      "fit": [
        -0.9938669800758362,
        0.0,
        0.9943556189537048
      ],
      "groups": [],
      "impact_r": 0.0,
      "name": "prop_binsignal_region_bin3_signal",
      "prefit": [
        -0.9999999999999999,
        0.0,
        0.9999999999999999
      ],
      "r": [
        5.399326818977812e-17,
        5.399326818977812e-17,
        5.399326818977812e-17
      ],
      "type": "Gaussian"
    },
    {
      "fit": [
        2.325361728668213,
        4.0,
        6.331540107727051
      ],
      "groups": [],
      "impact_r": 0.00010169255983788331,
      "name": "prop_binsignal_region_bin3_ttH",
      "prefit": [
        2.318494152717885,
        3.9999999999999996,
        6.346328819503796
      ],
      "r": [
        8.573808736400679e-05,
        5.399326818977812e-17,
        -0.00010169255983782932
      ],
      "type": "Poisson"
    },
    {
      "fit": [
        0.3041076064109802,
        1.0,
        2.3477165699005127
      ],
      "groups": [],
      "impact_r": 6.21305443929117e-05,
      "name": "prop_binsignal_region_bin3_ttW",
      "prefit": [
        0.30170955445432013,
        1.0000000000000002,
        2.357685579639466
      ],
      "r": [
        3.490185918053612e-05,
        5.399326818977812e-17,
        -6.21305443928577e-05
      ],
      "type": "Poisson"
    },
    {
      "fit": [
        1.590848684310913,
        3.0,
        5.065407752990723
      ],
      "groups": [],
      "impact_r": 0.00017342295905114894,
      "name": "prop_binsignal_region_bin3_ttZ",
      "prefit": [
        1.5839744900812804,
        2.9999999999999996,
        5.080237864900868
      ],
      "r": [
        0.00015704394900240004,
        5.399326818977812e-17,
        -0.00017342295905109495
      ],
      "type": "Poisson"
    },
    {
      "fit": [
        -0.9034529328346252,
        5.4643789493269423e-17,
        0.9826866984367371
      ],
      "groups": [],
      "impact_r": 0.0016768878558651285,
      "name": "prop_binsignal_region_bin4_WZ",
      "prefit": [
        -0.9999999999999999,
        0.0,
        0.9999999999999999
      ],
      "r": [
        6.732895491134983e-17,
        6.732895491134983e-17,
        -0.0016768878558650613
      ],
      "type": "Gaussian"
    },
    {
      "fit": [
        3.881308078765869,
        6.0,
        8.77540397644043
      ],
      "groups": [],
      "impact_r": 0.00014024834672460144,
      "name": "prop_binsignal_region_bin4_ZZ",
      "prefit": [
        3.8718786486154335,
        6.0,
        8.793563398676877
      ],
      "r": [
        0.0001174773060483858,
        5.399326818977812e-17,
        -0.00014024834672454745
      ],
      "type": "Poisson"
    },
    {
      "fit": [
        4.688354015350342,
        7.0,
        9.970405578613281
      ],
      "groups": [],
      "impact_r": 0.00019668941968126034,
      "name": "prop_binsignal_region_bin4_others",
      "prefit": [
        4.676546212856283,
        7.0,
        9.989068255581575
      ],
      "r": [
        0.00017494411440566182,
        5.399326818977812e-17,
        -0.00019668941968120635
      ],
      "type": "Poisson"
    },
    {
      "fit": [
        -0.9938669800758362,
        0.0,
        0.9943556189537048
      ],
      "groups": [],
      "impact_r": 0.0,
      "name": "prop_binsignal_region_bin4_signal",
      "prefit": [
        -0.9999999999999999,
        0.0,
        0.9999999999999999
      ],
      "r": [
        5.399326818977812e-17,
        5.399326818977812e-17,
        5.399326818977812e-17
      ],
      "type": "Gaussian"
    },
    {
      "fit": [
        -0.9939378499984741,
        0.0,
        0.9942957162857056
      ],
      "groups": [],
      "impact_r": 0.0003652570303529105,
      "name": "prop_binsignal_region_bin4_ttW",
      "prefit": [
        -0.9999999999999999,
        0.0,
        0.9999999999999999
      ],
      "r": [
        0.0003652570303529501,
        3.957337929572091e-17,
        -0.0002896860532928258
      ],
      "type": "Gaussian"
    },
    {
      "fit": [
        3.882889986038208,
        6.0,
        8.774720191955566
      ],
      "groups": [],
      "impact_r": 0.000841799599584138,
      "name": "prop_binsignal_region_bin4_ttZ",
      "prefit": [
        3.8718786486154335,
        6.0,
        8.793563398676877
      ],
      "r": [
        0.000841799599584192,
        5.399326818977812e-17,
        -0.0006513155531138182
      ],
      "type": "Poisson"
    },
    {
      "fit": [
        0.3047753870487213,
        1.0,
        2.3440494537353516
      ],
      "groups": [],
      "impact_r": 0.0028439711313694178,
      "name": "prop_binsignal_region_bin5_WZ",
      "prefit": [
        0.30170955445432013,
        1.0000000000000002,
        2.357685579639466
      ],
      "r": [
        0.0028439711313694715,
        5.399326818977812e-17,
        -0.0027314722537994385
      ],
      "type": "Poisson"
    },
    {
      "fit": [
        1.5910295248031616,
        3.0,
        5.066847324371338
      ],
      "groups": [],
      "impact_r": 0.000565088470466489,
      "name": "prop_binsignal_region_bin5_ZZ",
      "prefit": [
        1.5839744900812804,
        2.9999999999999996,
        5.080237864900868
      ],
      "r": [
        0.00042942367144860327,
        5.399326818977812e-17,
        -0.000565088470466435
      ],
      "type": "Poisson"
    },
    {
      "fit": [
        -0.9938891530036926,
        0.0,
        0.9943352341651917
      ],
      "groups": [],
      "impact_r": 0.000573798315599526,
      "name": "prop_binsignal_region_bin5_others",
      "prefit": [
        -0.9999999999999999,
        0.0,
        0.9999999999999999
      ],
      "r": [
        0.0005737983155995607,
        3.469446951953614e-17,
        -0.0005110197234898806
      ],
      "type": "Gaussian"
    },
    {
      "fit": [
        -0.9938669800758362,
        0.0,
        0.9943556189537048
      ],
      "groups": [],
      "impact_r": 0.0,
      "name": "prop_binsignal_region_bin5_signal",
      "prefit": [
        -0.9999999999999999,
        0.0,
        0.9999999999999999
      ],
      "r": [
        5.399326818977812e-17,
        5.399326818977812e-17,
        5.399326818977812e-17
      ],
      "type": "Gaussian"
    },
    {
      "fit": [
        0.9026827216148376,
        2.0,
        3.7536284923553467
      ],
      "groups": [],
      "impact_r": 0.0006923605687916819,
      "name": "prop_binsignal_region_bin5_ttH",
      "prefit": [
        0.897575384672683,
        1.9999999999999993,
        3.7654321135285054
      ],
      "r": [
        0.0004934642929583788,
        5.399326818977812e-17,
        -0.0006923605687916279
      ],
      "type": "Poisson"
    },
    {
      "fit": [
        -0.9939234256744385,
        0.0,
        0.9943062663078308
      ],
      "groups": [],
      "impact_r": 0.0008846063865348081,
      "name": "prop_binsignal_region_bin5_ttW",
      "prefit": [
        -0.9999999999999999,
        0.0,
        0.9999999999999999
      ],
      "r": [
        0.0008846063865348697,
        6.158268339717665e-17,
        -0.0007440813351422548
      ],
      "type": "Gaussian"
    },
    {
      "fit": [
        -0.9933656454086304,
        0.0,
        0.9939494132995605
      ],
      "groups": [],
      "impact_r": 0.002211550949141383,
      "name": "prop_binsignal_region_bin5_ttZ",
      "prefit": [
        -0.9999999999999999,
        0.0,
        0.9999999999999999
      ],
      "r": [
        0.002211550949141383,
        0.0,
        -0.0015109184896573424
      ],
      "type": "Gaussian"
    },
    {
      "fit": [
        0.3045169413089752,
        1.0,
        2.345991373062134
      ],
      "groups": [],
      "impact_r": 0.005396365653723532,
      "name": "prop_binsignal_region_bin6_WZ",
      "prefit": [
        0.30170955445432013,
        1.0000000000000002,
        2.357685579639466
      ],
      "r": [
        0.003432502970099449,
        5.399326818977812e-17,
        -0.005396365653723478
      ],
      "type": "Poisson"
    },
    {
      "fit": [
        3.092327833175659,
        5.0,
        7.56536340713501
      ],
      "groups": [],
      "impact_r": 0.00047600522520957326,
      "name": "prop_binsignal_region_bin6_ZZ",
      "prefit": [
        3.084097908968684,
        5.0,
        7.581106198937643
      ],
      "r": [
        0.0003556743904482573,
        5.399326818977812e-17,
        -0.00047600522520951927
      ],
      "type": "Poisson"
    },
    {
      "fit": [
        1.5896698236465454,
        3.0,
        5.066873073577881
      ],
      "groups": [],
      "impact_r": 0.000742427771911079,
      "name": "prop_binsignal_region_bin6_others",
      "prefit": [
        1.5839744900812804,
        2.9999999999999996,
        5.080237864900868
      ],
      "r": [
        0.0005101461429148912,
        5.399326818977812e-17,
        -0.000742427771911025
      ],
      "type": "Poisson"
    },
    {
      "fit": [
        -0.9938669800758362,
        0.0,
        0.9943556189537048
      ],
      "groups": [],
      "impact_r": 0.0,
      "name": "prop_binsignal_region_bin6_signal",
      "prefit": [
        -0.9999999999999999,
        0.0,
        0.9999999999999999
      ],
      "r": [
        5.399326818977812e-17,
        5.399326818977812e-17,
        5.399326818977812e-17
      ],
      "type": "Gaussian"
    },
    {
      "fit": [
        2.325354814529419,
        4.0,
        6.3315229415893555
      ],
      "groups": [],
      "impact_r": 0.0020965957082808555,
      "name": "prop_binsignal_region_bin6_ttH",
      "prefit": [
        2.318494152717885,
        3.9999999999999996,
        6.346328819503796
      ],
      "r": [
        0.001537057338282466,
        5.399326818977812e-17,
        -0.0020965957082808018
      ],
      "type": "Poisson"
    },
    {
      "fit": [
        -0.9938740134239197,
        0.0,
        0.9943487048149109
      ],
      "groups": [],
      "impact_r": 0.0006949942326172839,
      "name": "prop_binsignal_region_bin6_ttW",
      "prefit": [
        -0.9999999999999999,
        0.0,
        0.9999999999999999
      ],
      "r": [
        0.0006949942326173186,
        3.469446951953614e-17,
        -0.0006905909976921976
      ],
      "type": "Gaussian"
    },
    {
      "fit": [
        1.590966820716858,
        3.0,
        5.066768646240234
      ],
      "groups": [],
      "impact_r": 0.0024556387215853275,
      "name": "prop_binsignal_region_bin6_ttZ",
      "prefit": [
        1.5839744900812804,
        2.9999999999999996,
        5.080237864900868
      ],
      "r": [
        0.0017159126000478864,
        5.399326818977812e-17,
        -0.0024556387215852737
      ],
      "type": "Poisson"
    },
    {
      "fit": [
        0.9032278656959534,
        2.0,
        3.7489678859710693
      ],
      "groups": [],
      "impact_r": 0.003034484805539304,
      "name": "prop_binsignal_region_bin7_WZ",
      "prefit": [
        0.897575384672683,
        1.9999999999999993,
        3.7654321135285054
      ],
      "r": [
        0.0023869306314736605,
        5.399326818977812e-17,
        -0.0030344848055392504
      ],
      "type": "Poisson"
    },
    {
      "fit": [
        3.881312370300293,
        6.0,
        8.775431632995605
      ],
      "groups": [],
      "impact_r": 0.00012384184810804015,
      "name": "prop_binsignal_region_bin7_ZZ",
      "prefit": [
        3.8718786486154335,
        6.0,
        8.793563398676877
      ],
      "r": [
        9.532204421702772e-05,
        5.399326818977812e-17,
        -0.00012384184810798615
      ],
      "type": "Poisson"
    },
    {
      "fit": [
        0.31291255354881287,
        1.0,
        2.276284694671631
      ],
      "groups": [],
      "impact_r": 0.018376672640442793,
      "name": "prop_binsignal_region_bin7_nonprompt",
      "prefit": [
        0.30170955445432013,
        1.0000000000000002,
        2.357685579639466
      ],
      "r": [
        0.018376672640442848,
        5.399326818977812e-17,
        -0.008443635888397694
      ],
      "type": "Poisson"
    },
    {
      "fit": [
        1.5896751880645752,
        3.0,
        5.066879749298096
      ],
      "groups": [],
      "impact_r": 0.000222457354539128,
      "name": "prop_binsignal_region_bin7_others",
      "prefit": [
        1.5839744900812804,
        2.9999999999999996,
        5.080237864900868
      ],
      "r": [
        0.0001540394441690296,
        5.399326818977812e-17,
        -0.000222457354539074
      ],
      "type": "Poisson"
    },
    {
      "fit": [
        -0.9938669800758362,
        0.0,
        0.9943556189537048
      ],
      "groups": [],
      "impact_r": 0.0,
      "name": "prop_binsignal_region_bin7_signal",
      "prefit": [
        -0.9999999999999999,
        0.0,
        0.9999999999999999
      ],
      "r": [
        5.399326818977812e-17,
        5.399326818977812e-17,
        5.399326818977812e-17
      ],
      "type": "Gaussian"
    },
    {
      "fit": [
        0.30411937832832336,
        1.0,
        2.347731590270996
      ],
      "groups": [],
      "impact_r": 0.00015146487567113524,
      "name": "prop_binsignal_region_bin7_ttH",
      "prefit": [
        0.30170955445432013,
        1.0000000000000002,
        2.357685579639466
      ],
      "r": [
        7.888663094490767e-05,
        5.399326818977812e-17,
        -0.00015146487567108124
      ],
      "type": "Poisson"
    },
    {
      "fit": [
        3.092311382293701,
        5.0,
        7.5653276443481445
      ],
      "groups": [],
      "impact_r": 0.0004709711065516416,
      "name": "prop_binsignal_region_bin7_ttZ",
      "prefit": [
        3.084097908968684,
        5.0,
        7.581106198937643
      ],
      "r": [
        0.00036180848837830126,
        5.399326818977812e-17,
        -0.0004709711065515876
      ],
      "type": "Poisson"
    },
    {
      "fit": [
        0.9024961590766907,
        2.0,
        3.752224922180176
      ],
      "groups": [],
      "impact_r": 0.0010118851205334607,
      "name": "prop_binsignal_region_bin8_WZ",
      "prefit": [
        0.897575384672683,
        1.9999999999999993,
        3.7654321135285054
      ],
      "r": [
        0.0007030933629721403,
        5.399326818977812e-17,
        -0.0010118851205334067
      ],
      "type": "Poisson"
    },
    {
      "fit": [
        7.1765031814575195,
        10.0,
        13.483833312988281
      ],
      "groups": [],
      "impact_r": 6.285176641546001e-05,
      "name": "prop_binsignal_region_bin8_ZZ",
      "prefit": [
        7.161895381748982,
        10.0,
        13.504032638931708
      ],
      "r": [
        5.1289433031342924e-05,
        5.399326818977812e-17,
        -6.285176641540602e-05
      ],
      "type": "Poisson"
    },
    {
      "fit": [
        0.332327276468277,
        1.0,
        2.2026681900024414
      ],
      "groups": [],
      "impact_r": 0.024204015731811468,
      "name": "prop_binsignal_region_bin8_nonprompt",
      "prefit": [
        0.30170955445432013,
        1.0000000000000002,
        2.357685579639466
      ],
      "r": [
        0.024204015731811523,
        5.399326818977812e-17,
        -0.006548555567860603
      ],
      "type": "Poisson"
    },
    {
      "fit": [
        0.9027124643325806,
        2.0,
        3.7536938190460205
      ],
      "groups": [],
      "impact_r": 7.603455742360835e-05,
      "name": "prop_binsignal_region_bin8_others",
      "prefit": [
        0.897575384672683,
        1.9999999999999993,
        3.7654321135285054
      ],
      "r": [
        4.793134212377481e-05,
        5.399326818977812e-17,
        -7.603455742355436e-05
      ],
      "type": "Poisson"
    },
    {
      "fit": [
        -0.9938669800758362,
        0.0,
        0.9943556189537048
      ],
      "groups": [],
      "impact_r": 0.0,
      "name": "prop_binsignal_region_bin8_signal",
      "prefit": [
        -0.9999999999999999,
        0.0,
        0.9999999999999999
      ],
      "r": [
        5.399326818977812e-17,
        5.399326818977812e-17,
        5.399326818977812e-17
      ],
      "type": "Gaussian"
    },
    {
      "fit": [
        0.902711033821106,
        2.0,
        3.753690004348755
      ],
      "groups": [],
      "impact_r": 0.00011819782957905715,
      "name": "prop_binsignal_region_bin8_ttH",
      "prefit": [
        0.897575384672683,
        1.9999999999999993,
        3.7654321135285054
      ],
      "r": [
        7.48071470297873e-05,
        5.399326818977812e-17,
        -0.00011819782957900316
      ],
      "type": "Poisson"
    },
    {
      "fit": [
        -0.9938710927963257,
        0.0,
        0.9943515658378601
      ],
      "groups": [],
      "impact_r": 0.00013647064042739826,
      "name": "prop_binsignal_region_bin8_ttW",
      "prefit": [
        -0.9999999999999999,
        0.0,
        0.9999999999999999
      ],
      "r": [
        0.00013647064042743295,
        3.469446951953614e-17,
        -0.0001343659678241238
      ],
      "type": "Gaussian"
    },
    {
      "fit": [
        -0.9938842058181763,
        0.0,
        0.9943386912345886
      ],
      "groups": [],
      "impact_r": 0.00027360461535858515,
      "name": "prop_binsignal_region_bin8_ttZ",
      "prefit": [
        -0.9999999999999999,
        0.0,
        0.9999999999999999
      ],
      "r": [
        0.0002736046153586358,
        5.063224145507306e-17,
        -0.0002651048998814076
      ],
      "type": "Gaussian"
    },
    {
      "fit": [
        -0.9898277521133423,
        3.0357660829594124e-18,
        0.9919753074645996
      ],
      "groups": [],
      "impact_r": 0.006856806110590637,
      "name": "prop_binsignal_region_bin9_WZ",
      "prefit": [
        -0.9999999999999999,
        0.0,
        0.9999999999999999
      ],
      "r": [
        0.006856806110590696,
        5.919743861770854e-17,
        -0.0025804350152611732
      ],
      "type": "Gaussian"
    },
    {
      "fit": [
        -0.99388188123703,
        0.0,
        0.9943416118621826
      ],
      "groups": [],
      "impact_r": 0.0003966358490287656,
      "name": "prop_binsignal_region_bin9_ZZ",
      "prefit": [
        -0.9999999999999999,
        0.0,
        0.9999999999999999
      ],
      "r": [
        0.00039663584902882576,
        6.01732205729455e-17,
        -0.00036388306762091815
      ],
      "type": "Gaussian"
    },
    {
      "fit": [
        3.881304979324341,
        6.0,
        8.775382995605469
      ],
      "groups": [],
      "impact_r": 0.0004211591149215195,
      "name": "prop_binsignal_region_bin9_others",
      "prefit": [
        3.8718786486154335,
        6.0,
        8.793563398676877
      ],
      "r": [
        0.00035133323399350047,
        5.399326818977812e-17,
        -0.0004211591149214655
      ],
      "type": "Poisson"
    },
    {
      "fit": [
        -0.9938669800758362,
        0.0,
        0.9943556189537048
      ],
      "groups": [],
      "impact_r": 0.0,
      "name": "prop_binsignal_region_bin9_signal",
      "prefit": [
        -0.9999999999999999,
        0.0,
        0.9999999999999999
      ],
      "r": [
        5.399326818977812e-17,
        5.399326818977812e-17,
        5.399326818977812e-17
      ],
      "type": "Gaussian"
    },
    {
      "fit": [
        0.30411460995674133,
        1.0,
        2.3477258682250977
      ],
      "groups": [],
      "impact_r": 0.00030208274256443416,
      "name": "prop_binsignal_region_bin9_ttH",
      "prefit": [
        0.30170955445432013,
        1.0000000000000002,
        2.357685579639466
      ],
      "r": [
        0.00016464431246276945,
        5.399326818977812e-17,
        -0.00030208274256438017
      ],
      "type": "Poisson"
    },
    {
      "fit": [
        1.5909903049468994,
        3.0,
        5.066796779632568
      ],
      "groups": [],
      "impact_r": 0.0007492583245039526,
      "name": "prop_binsignal_region_bin9_ttW",
      "prefit": [
        1.5839744900812804,
        2.9999999999999996,
        5.080237864900868
      ],
      "r": [
        0.0005964656011201441,
        5.399326818977812e-17,
        -0.0007492583245038986
      ],
      "type": "Poisson"
    },
    {
      "fit": [
        3.883253574371338,
        6.0,
        8.774982452392578
      ],
      "groups": [],
      "impact_r": 0.0012341459514572677,
      "name": "prop_binsignal_region_bin9_ttZ",
      "prefit": [
        3.8718786486154335,
        6.0,
        8.793563398676877
      ],
      "r": [
        0.0012341459514573216,
        5.399326818977812e-17,
        -0.0012220647186040878
      ],
      "type": "Poisson"
    }
  ]
}